{
  "base": "USD",
  "currencies": [
    "USD",
    "EUR",
    "RUB",
    "KZT",
    "GEL",
    "GBP"
  ],
  "updatedAt": "Sun, 03 May 2026 00:02:31 +0000",
  "points": [
    {
      "date": "2026-04-03",
      "rates": {
        "USD": 1,
        "EUR": 0.866243,
        "RUB": 79.057722,
        "KZT": 465.007778,
        "GEL": 2.694851,
        "GBP": 0.755617
      }
    },
    {
      "date": "2026-04-08",
      "rates": {
        "USD": 1,
        "EUR": 0.860695,
        "RUB": 78.711681,
        "KZT": 465.662654,
        "GEL": 2.692154,
        "GBP": 0.752084
      }
    },
    {
      "date": "2026-04-09",
      "rates": {
        "USD": 1,
        "EUR": 0.856399,
        "RUB": 78.532386,
        "KZT": 477.727397,
        "GEL": 2.694422,
        "GBP": 0.745362
      }
    },
    {
      "date": "2026-04-10",
      "rates": {
        "USD": 1,
        "EUR": 0.855422,
        "RUB": 77.807871,
        "KZT": 477.486328,
        "GEL": 2.695191,
        "GBP": 0.744815
      }
    },
    {
      "date": "2026-04-11",
      "rates": {
        "USD": 1,
        "EUR": 0.853304,
        "RUB": 77.383563,
        "KZT": 478.496748,
        "GEL": 2.694975,
        "GBP": 0.743471
      }
    },
    {
      "date": "2026-04-12",
      "rates": {
        "USD": 1,
        "EUR": 0.853488,
        "RUB": 77.408243,
        "KZT": 478.378441,
        "GEL": 2.694911,
        "GBP": 0.743547
      }
    },
    {
      "date": "2026-04-13",
      "rates": {
        "USD": 1,
        "EUR": 0.85611,
        "RUB": 77.078049,
        "KZT": 473.849887,
        "GEL": 2.692249,
        "GBP": 0.745882
      }
    },
    {
      "date": "2026-04-14",
      "rates": {
        "USD": 1,
        "EUR": 0.852141,
        "RUB": 76.145176,
        "KZT": 475.095277,
        "GEL": 2.697787,
        "GBP": 0.742062
      }
    },
    {
      "date": "2026-04-15",
      "rates": {
        "USD": 1,
        "EUR": 0.847706,
        "RUB": 75.503022,
        "KZT": 475.731327,
        "GEL": 2.694082,
        "GBP": 0.737401
      }
    },
    {
      "date": "2026-04-16",
      "rates": {
        "USD": 1,
        "EUR": 0.847508,
        "RUB": 75.545633,
        "KZT": 474.190894,
        "GEL": 2.691127,
        "GBP": 0.737078
      }
    },
    {
      "date": "2026-04-17",
      "rates": {
        "USD": 1,
        "EUR": 0.849024,
        "RUB": 76.321083,
        "KZT": 471.285198,
        "GEL": 2.690835,
        "GBP": 0.73885
      }
    },
    {
      "date": "2026-04-18",
      "rates": {
        "USD": 1,
        "EUR": 0.848449,
        "RUB": 76.032102,
        "KZT": 469.976135,
        "GEL": 2.691069,
        "GBP": 0.73885
      }
    },
    {
      "date": "2026-04-19",
      "rates": {
        "USD": 1,
        "EUR": 0.848763,
        "RUB": 76.111323,
        "KZT": 470.547525,
        "GEL": 2.689902,
        "GBP": 0.739001
      }
    },
    {
      "date": "2026-04-20",
      "rates": {
        "USD": 1,
        "EUR": 0.851098,
        "RUB": 76.045071,
        "KZT": 470.075456,
        "GEL": 2.687725,
        "GBP": 0.74115
      }
    },
    {
      "date": "2026-04-21",
      "rates": {
        "USD": 1,
        "EUR": 0.848957,
        "RUB": 75.082931,
        "KZT": 468.051201,
        "GEL": 2.689916,
        "GBP": 0.73926
      }
    },
    {
      "date": "2026-04-22",
      "rates": {
        "USD": 1,
        "EUR": 0.851081,
        "RUB": 75.024479,
        "KZT": 464.39996,
        "GEL": 2.690277,
        "GBP": 0.740163
      }
    },
    {
      "date": "2026-04-23",
      "rates": {
        "USD": 1,
        "EUR": 0.85298,
        "RUB": 75.043299,
        "KZT": 462.941718,
        "GEL": 2.688863,
        "GBP": 0.740523
      }
    },
    {
      "date": "2026-04-24",
      "rates": {
        "USD": 1,
        "EUR": 0.855327,
        "RUB": 75.075083,
        "KZT": 464.62766,
        "GEL": 2.68978,
        "GBP": 0.741737
      }
    },
    {
      "date": "2026-04-25",
      "rates": {
        "USD": 1,
        "EUR": 0.853951,
        "RUB": 75.399755,
        "KZT": 464.245336,
        "GEL": 2.694145,
        "GBP": 0.740689
      }
    },
    {
      "date": "2026-04-26",
      "rates": {
        "USD": 1,
        "EUR": 0.854043,
        "RUB": 75.386258,
        "KZT": 464.255933,
        "GEL": 2.693325,
        "GBP": 0.74068
      }
    },
    {
      "date": "2026-04-27",
      "rates": {
        "USD": 1,
        "EUR": 0.854233,
        "RUB": 75.322373,
        "KZT": 464.324593,
        "GEL": 2.689025,
        "GBP": 0.740223
      }
    },
    {
      "date": "2026-04-28",
      "rates": {
        "USD": 1,
        "EUR": 0.852627,
        "RUB": 74.926809,
        "KZT": 459.474983,
        "GEL": 2.689811,
        "GBP": 0.738414
      }
    },
    {
      "date": "2026-04-29",
      "rates": {
        "USD": 1,
        "EUR": 0.8541,
        "RUB": 75.127272,
        "KZT": 458.769779,
        "GEL": 2.690002,
        "GBP": 0.740257
      }
    },
    {
      "date": "2026-04-30",
      "rates": {
        "USD": 1,
        "EUR": 0.855579,
        "RUB": 75.109519,
        "KZT": 462.367206,
        "GEL": 2.68768,
        "GBP": 0.741191
      }
    },
    {
      "date": "2026-05-01",
      "rates": {
        "USD": 1,
        "EUR": 0.853339,
        "RUB": 74.983401,
        "KZT": 463.419275,
        "GEL": 2.688306,
        "GBP": 0.737561
      }
    },
    {
      "date": "2026-05-02",
      "rates": {
        "USD": 1,
        "EUR": 0.852919,
        "RUB": 75.028001,
        "KZT": 463.447432,
        "GEL": 2.688871,
        "GBP": 0.737317
      }
    },
    {
      "date": "2026-05-03",
      "rates": {
        "USD": 1,
        "EUR": 0.852795,
        "RUB": 75.02174,
        "KZT": 463.429114,
        "GEL": 2.688709,
        "GBP": 0.737086
      }
    }
  ]
}
